chemical_analysis_tool/__init__.py
databuster-0.2.2.dist-info/LICENSE
databuster-0.2.2.dist-info/METADATA
databuster-0.2.2.dist-info/WHEEL
databuster-0.2.2.dist-info/entry_points.txt
databuster-0.2.2.dist-info/top_level.txt
databuster-0.2.2.dist-info/RECORD
