Metadata-Version: 2.1
Name: databuster
Version: 0.2.2
Summary: A comprehensive chemical compound analysis platform for drug discovery research, developed by Suneel Kumar BVS, Ph.D., ATOMICAS AI SOLUTIONS PRIVATE LIMITED (https://theatomicas.io)
Author: Suneel Kumar BVS, Ph.D.
Author-email: "Suneel Kumar BVS, Ph.D." <suneelkumar.bvs@gmail.com>
License: MIT License
Project-URL: Homepage, https://github.com/suneelbvs/databuster
Project-URL: Repository, https://github.com/suneelbvs/databuster.git
Keywords: chemistry,drug-discovery,molecular-analysis,chemical-compounds,cheminformatics,databuster
Platform: unix
Platform: linux
Platform: osx
Platform: win32
Classifier: Development Status :: 4 - Beta
Classifier: Intended Audience :: Science/Research
Classifier: License :: OSI Approved :: MIT License
Classifier: Programming Language :: Python :: 3
Classifier: Programming Language :: Python :: 3.11
Classifier: Topic :: Scientific/Engineering :: Chemistry
Classifier: Topic :: Scientific/Engineering :: Bio-Informatics
Classifier: Topic :: Software Development :: Libraries :: Python Modules
Requires-Python: >=3.11
License-File: LICENSE
Requires-Dist: build>=1.2.2.post1
Requires-Dist: cairosvg>=2.7.1
Requires-Dist: chembl-webresource-client>=0.10.9
Requires-Dist: deepchem>=2.8.0
Requires-Dist: molvs>=0.1.1
Requires-Dist: numpy<2
Requires-Dist: pandas>=2.0.0
Requires-Dist: plotly>=5.24.1
Requires-Dist: py3dmol>=2.4.0
Requires-Dist: python-dotenv>=1.0.1
Requires-Dist: rdkit>=2.2.3
Requires-Dist: scipy>=1.14.1
Requires-Dist: setuptools>=75.6.0
Requires-Dist: streamlit>=1.39.0
Requires-Dist: tdc>=0.1.0
Requires-Dist: twine==6.0.1
Requires-Dist: wheel>=0.45.1
Provides-Extra: dev
Requires-Dist: pytest>=7.0; extra == "dev"
Requires-Dist: pytest-cov>=4.0; extra == "dev"
Requires-Dist: black>=23.0; extra == "dev"
Requires-Dist: isort>=5.0; extra == "dev"
Requires-Dist: mypy>=1.0; extra == "dev"
